curp/__about__.py
curp/__init__.py
curp/altisonantes.py
curp/chars.py
curp/cli.py
curp/curp.py
curp/estados.py
curp/exceptions.py
curp/features.py
curp/py.typed
CURPSuite-2.6.1.dist-info/LICENSE
CURPSuite-2.6.1.dist-info/METADATA
CURPSuite-2.6.1.dist-info/WHEEL
CURPSuite-2.6.1.dist-info/entry_points.txt
CURPSuite-2.6.1.dist-info/top_level.txt
CURPSuite-2.6.1.dist-info/RECORD
