Metadata-Version: 2.1
Name: CURPSuite
Version: 2.6.1
Summary: Análisis y validación de la CURP Mexicana
Author-email: Jacob Sánchez <jacobszpz@protonmail.com>
Project-URL: Homepage, https://curpsuite.readthedocs.io
Project-URL: Repository, https://github.com/jacobszpz/CURPSuite
Keywords: CURP,validation,analysis,Mexico
Classifier: Development Status :: 5 - Production/Stable
Classifier: License :: OSI Approved :: GNU General Public License v2 (GPLv2)
Classifier: Programming Language :: Python :: 3.8
Classifier: Programming Language :: Python :: 3.9
Classifier: Programming Language :: Python :: 3.10
Classifier: Intended Audience :: Developers
Classifier: Intended Audience :: Information Technology
Classifier: Intended Audience :: Legal Industry
Classifier: Intended Audience :: Science/Research
Classifier: Natural Language :: Spanish
Requires-Python: >=3.8
License-File: LICENSE
Requires-Dist: unidecode
Provides-Extra: test
Requires-Dist: pytest ; extra == 'test'
Requires-Dist: hypothesis ; extra == 'test'
Requires-Dist: coverage ; extra == 'test'
